robinhood_client/__init__.py
robinhood_client/common/__init__.py
robinhood_client/common/auth.py
robinhood_client/common/clients.py
robinhood_client/common/constants.py
robinhood_client/common/cursor.py
robinhood_client/common/enums.py
robinhood_client/common/exceptions.py
robinhood_client/common/logging.py
robinhood_client/common/schema.py
robinhood_client/common/session.py
robinhood_client/data/__init__.py
robinhood_client/data/instruments.py
robinhood_client/data/orders.py
robinhood_client/data/requests.py
robinhood_client/trading/__init__.py
robinhood_client-0.3.1.dist-info/METADATA
robinhood_client-0.3.1.dist-info/WHEEL
robinhood_client-0.3.1.dist-info/licenses/LICENSE
robinhood_client-0.3.1.dist-info/RECORD
