Metadata-Version: 2.4
Name: robinhood-client
Version: 0.3.1
Summary: An unofficial Python REST client for Robinhood API.
License: MIT License
License-File: LICENSE
Keywords: robinhood,api,client,stocks,trading,crypto,investing
Author: Ryan Miller
Author-email: mrzodge@gmail.com
Requires-Python: >=3.10
Classifier: Programming Language :: Python :: 3
Classifier: Programming Language :: Python :: 3 :: Only
Classifier: Programming Language :: Python :: 3.10
Classifier: Programming Language :: Python :: 3.11
Classifier: Programming Language :: Python :: 3.12
Classifier: Programming Language :: Python :: 3.13
Classifier: Operating System :: OS Independent
Provides-Extra: dev
Requires-Dist: cryptography (>=45.0.6,<45.1.0)
Requires-Dist: pydantic (>=2.11.7,<2.12.0)
Requires-Dist: pyotp (>=2.9.0,<2.10.0)
Requires-Dist: pytest (>=8.4.1,<8.5.0) ; extra == "dev"
Requires-Dist: pytest-dotenv (>=0.5.2,<0.6.0) ; extra == "dev"
Requires-Dist: python-dateutil (>=2.9.0.post0,<2.10.0) ; extra == "dev"
Requires-Dist: python-dotenv (>=1.1.1,<1.2.0)
Requires-Dist: requests (>=2.32.4,<2.33.0)
Requires-Dist: ruff (>=0.12.9,<0.13.0) ; extra == "dev"
Project-URL: Homepage, https://github.com/RvanMiller/robinhood-client
Project-URL: Repository, https://github.com/RvanMiller/robinhood-client
